{"2_time":"158.373","14_time":"40.654","p8_response_3":"{\"6-1\":\"1\",\"7-1\":\"4\",\"7-2\":\"4\",\"7-3\":\"5\",\"8-1\":\"4\",\"9-1\":[\"Social Media\",\"Financial Websites\"]}","p12_response":"{\"1-1\":\"4\",\"2-1\":\"4\",\"3-1\":\"4\",\"3-2\":\"5\",\"3-3\":\"4\",\"3-4\":\"4\",\"4-1\":\"2\",\"5-1\":\"4\",\"6-1\":\"5\",\"7-1\":\"5\",\"8-1\":\"I used a variation of the strategy presented in the design.\"}","12_time":"47.062","password2":"sa30#*","p3_response":"{\"1-1\":\"4\",\"1-2\":\"5\",\"1-3\":\"3\",\"1-4\":\"5\"}","5_time":"9.092","10_time":"131.181","did":"3","8_time":"183.718","p8_response_2":"{\"2-1\":\"6\",\"3-1\":\"4\",\"3-2\":\"5\",\"3-3\":\"3\",\"4-1\":\"4\",\"13-1\":\"5\"}","7_time":"120.188","p7_response_2":"{\"1-13\":\"2\",\"1-16\":\"2\",\"1-14\":\"2\",\"1-15\":\"3\",\"1-17\":\"3\",\"1-12\":\"3\",\"1-11\":\"3\"}","4_time":"24.084","11_time":"137.23","p14_response":"{\"1-1\":\"Man\",\"2-1\":\"25-29 years old\",\"3-1\":[\"Asian\"],\"4-1\":\"Four-year College Degree\",\"5-1\":\"Computer Science/Engineering, and Information Technology (IT)\",\"6-1\":\"Educational institution\",\"7-1\":\"Formal training\",\"8-1\":\"Self-taught\",\"9-1\":\"6\"}","p7_response_1":"{\"1-8\":\"4\",\"1-4\":\"4\",\"1-2\":\"3\",\"1-5\":\"3\",\"1-7\":\"4\",\"1-10\":\"3\",\"1-3\":\"5\",\"1-1\":\"4\",\"1-9\":\"4\",\"1-6\":\"4\"}","p8_response_1":"{\"1-6\":\"4\",\"1-4\":\"4\",\"1-2\":\"5\",\"1-1\":\"4\",\"1-3\":\"5\",\"1-7\":\"4\",\"1-8\":\"5\",\"1-5\":\"4\"}","p8_response_4":"{\"10-1\":\"5\",\"11-1\":\"with the help of shybour security\"}","9_time":"6.997","13_time":"36.565","6_time":"27.517","giftcode":"Onl-A2DRJL37OEZ3B9"}