{"2_time":"1.666","14_time":"49.266","p8_response_3":"{\"6-1\":\"1\",\"7-1\":\"5\",\"7-2\":\"6\",\"7-3\":\"6\",\"8-1\":\"5\",\"9-1\":[\"E-commerce Websites\",\"Course Management Websites, e.g. Canvas, Blackboard, etc.\"]}","p12_response":"{\"1-1\":\"5\",\"2-1\":\"6\",\"3-1\":\"3\",\"3-2\":\"2\",\"3-3\":\"3\",\"3-4\":\"6\",\"4-1\":\"2\",\"5-1\":\"6\",\"6-1\":\"5\",\"7-1\":\"2\",\"8-1\":\"I used a variation of the strategy presented in the design.\"}","12_time":"22.393","password2":"imadhe3>_ast","p3_response":"{\"1-1\":\"6\",\"1-2\":\"3\",\"1-3\":\"2\",\"1-4\":\"5\"}","5_time":"6.418","10_time":"36.412","did":"1","8_time":"223.005","p8_response_2":"{\"2-1\":\"6\",\"3-1\":\"5\",\"3-2\":\"5\",\"3-3\":\"4\",\"4-1\":\"5\",\"13-1\":\"5\"}","7_time":"53.329","p7_response_2":"{\"1-14\":\"5\",\"1-16\":\"3\",\"1-17\":\"5\",\"1-13\":\"5\",\"1-11\":\"5\",\"1-15\":\"6\",\"1-12\":\"2\"}","6_time":"10.86","9_time":"6.614","11_time":"6.567","p14_response":"{\"1-1\":\"Man\",\"2-1\":\"30-34 years old\",\"3-1\":[\"White\"],\"4-1\":\"Four-year College Degree\",\"5-1\":\"Computer Science/Engineering, and Information Technology (IT)\",\"6-1\":\"Business or industry\",\"7-1\":\"Pursuing or completed a degree\",\"8-1\":\"Pursuing or completed a degree\",\"9-1\":\"6\"}","4_time":"11.314","p8_response_1":"{\"1-2\":\"5\",\"1-5\":\"5\",\"1-3\":\"5\",\"1-8\":\"2\",\"1-7\":\"3\",\"1-1\":\"3\",\"1-4\":\"5\",\"1-6\":\"3\"}","p7_response_1":"{\"1-9\":\"3\",\"1-1\":\"5\",\"1-10\":\"4\",\"1-4\":\"3\",\"1-7\":\"6\",\"1-5\":\"2\",\"1-3\":\"4\",\"1-2\":\"2\",\"1-8\":\"3\",\"1-6\":\"7\"}","p8_response_4":"{\"10-1\":\"5\",\"11-1\":\"The presentation is clear and easily understandable. The information is defined and well presented. \"}","13_time":"4.253","giftcode":"Inf-A3N0QZ9ZKUCTCQ"}